sslcompare/anssi.yaml
sslcompare/sslcompare.py
sslcompare/testssl.sh/CREDITS.md
sslcompare/testssl.sh/LICENSE
sslcompare/testssl.sh/bin/OPENSSL-LICENSE.txt
sslcompare/testssl.sh/bin/openssl.Linux.x86_64
sslcompare/testssl.sh/etc/Apple.pem
sslcompare/testssl.sh/etc/DST Root CA X3.txt
sslcompare/testssl.sh/etc/Java.pem
sslcompare/testssl.sh/etc/Linux.pem
sslcompare/testssl.sh/etc/Microsoft.pem
sslcompare/testssl.sh/etc/Mozilla.pem
sslcompare/testssl.sh/etc/README.md
sslcompare/testssl.sh/etc/SSLSocketClient.java
sslcompare/testssl.sh/etc/ca_hashes.txt
sslcompare/testssl.sh/etc/cipher-mapping.txt
sslcompare/testssl.sh/etc/client-simulation.txt
sslcompare/testssl.sh/etc/client-simulation.wiresharked.md
sslcompare/testssl.sh/etc/client-simulation.wiresharked.txt
sslcompare/testssl.sh/etc/common-primes.txt
sslcompare/testssl.sh/etc/curves-mapping.txt
sslcompare/testssl.sh/etc/curves.txt
sslcompare/testssl.sh/etc/openssl.cnf
sslcompare/testssl.sh/etc/tls_data.txt
sslcompare/testssl.sh/testssl.sh
sslcompare-1.7.2.dist-info/LICENSE
sslcompare-1.7.2.dist-info/METADATA
sslcompare-1.7.2.dist-info/WHEEL
sslcompare-1.7.2.dist-info/entry_points.txt
sslcompare-1.7.2.dist-info/RECORD
