Metadata-Version: 2.1
Name: sslcompare
Version: 1.7.2
Summary: Compares a server's cipher suites with a provided baseline
License: GPL-2.0-or-later
Author: Arthur Le Corguille
Requires-Python: >=3.8.0
Classifier: License :: OSI Approved :: GNU General Public License v2 or later (GPLv2+)
Classifier: Programming Language :: Python :: 3
Classifier: Programming Language :: Python :: 3.8
Classifier: Programming Language :: Python :: 3.9
Classifier: Programming Language :: Python :: 3.10
Classifier: Programming Language :: Python :: 3.11
Requires-Dist: click (>=8.1.3,<9.0.0)
Requires-Dist: pyyaml (>=6.0,<7.0)
